{"stem":"mähren","instances":[{"docId":"schoenbach005","docUri":"schoenbach005.html","score":1,"contexts":[{"form":"Mähren","weight":"1","pos":11,"context":" Zdisslawita Post Zdounek <mark>Mähren<\/mark>1. Sept. 911. Hochverehrte teure Frau!...","fid":"div__15"}]},{"docId":"schoenbach002","docUri":"schoenbach002.html","score":1,"contexts":[{"form":"Mähren","weight":"1","pos":2,"context":" Blansko in <mark>Mähren<\/mark>; 30t. October 1888. Hochverehrter Herr!...","fid":"div__26"}]},{"docId":"schoenbach001","docUri":"schoenbach001.html","score":1,"contexts":[{"form":"Mähren","weight":"1","pos":2,"context":" Habrovan in <mark>Mähren<\/mark>. 3' December 1898. Hochverehrter Herr!...","fid":"div__13"}]},{"docId":"schoenbach004","docUri":"schoenbach004.html","score":1,"contexts":[{"form":"Mähren","weight":"1","pos":2,"context":" Blansko in <mark>Mähren<\/mark>; 3' Januar 1888. Hochverehrter Herr Regierungsrath...","fid":"div__22"}]}]}